MANIFEST.in
README.rst
setup.cfg
setup.py
pluggdapps/__init__.py
pluggdapps/config.py
pluggdapps/const.py
pluggdapps/interfaces.py
pluggdapps/pa.py
pluggdapps/platform.py
pluggdapps/plugin.py
pluggdapps.egg-info/PKG-INFO
pluggdapps.egg-info/SOURCES.txt
pluggdapps.egg-info/dependency_links.txt
pluggdapps.egg-info/entry_points.txt
pluggdapps.egg-info/namespace_packages.txt
pluggdapps.egg-info/not-zip-safe
pluggdapps.egg-info/requires.txt
pluggdapps.egg-info/top_level.txt
pluggdapps/commands/__init__.py
pluggdapps/commands/commands.py
pluggdapps/commands/confdoc.py
pluggdapps/commands/erlport.py
pluggdapps/commands/ls.py
pluggdapps/commands/pviews.py
pluggdapps/commands/serve.py
pluggdapps/commands/unittest.py
pluggdapps/docroot/__init__.py
pluggdapps/docroot/docroot.py
pluggdapps/docroot/router.py
pluggdapps/docroot/views.py
pluggdapps/erl/__init__.py
pluggdapps/erl/codec.py
pluggdapps/erl/main.py
pluggdapps/erl/terms.py
pluggdapps/scaffolds/__init__.py
pluggdapps/scaffolds/env.py
pluggdapps/scaffolds/newapp.py
pluggdapps/scaffolds/env_template/Makefile
pluggdapps/scaffolds/env_template/README.rst
pluggdapps/scaffolds/env_template/cache/README
pluggdapps/scaffolds/env_template/db/configdb.sqlite3
pluggdapps/scaffolds/env_template/etc/master.ini
pluggdapps/scaffolds/env_template/etc/webadmin.ini
pluggdapps/scaffolds/newapp_template/__init__.py.tmpl
pluggdapps/scaffolds/newapp_template/interfaces.py.tmpl
pluggdapps/scaffolds/newapp_template/resource.py.tmpl
pluggdapps/scaffolds/newapp_template/router.py.tmpl
pluggdapps/scaffolds/newapp_template/view.py.tmpl
pluggdapps/scaffolds/newapp_template/{webapp_name}.py.tmpl
pluggdapps/scaffolds/newapp_template/static/README
pluggdapps/scaffolds/newapp_template/templates/README
pluggdapps/tests/__init__.py
pluggdapps/tests/test_asset.py
pluggdapps/tests/test_config.py
pluggdapps/tests/test_erlcodec.py
pluggdapps/tests/test_jsonlib.py
pluggdapps/tests/test_lib.py
pluggdapps/tests/test_path.py
pluggdapps/tests/test_platform.py
pluggdapps/tests/test_plugin.py
pluggdapps/tests/tests_cookie.py
pluggdapps/utils/__init__.py
pluggdapps/utils/asset.py
pluggdapps/utils/config.py
pluggdapps/utils/jsonlib.py
pluggdapps/utils/lib.py
pluggdapps/utils/merge.py
pluggdapps/utils/parsehttp.py
pluggdapps/utils/path.py
