Metadata-Version: 1.1
Name: pluggdapps
Version: 0.42dev
Summary: Pluggdapps component system, web framework
Home-page: http://pythonhosted.org/pluggdapps/
Author: prataprc
Author-email: prataprc@gmail.com
License: General Public License
Keywords: plugin,component,web,plugin,configuration
Platform: 
Classifier: Development Status :: 4 - Beta
Classifier: Environment :: Plugins
Classifier: Environment :: Web Environment
Classifier: Intended Audience :: Developers
Classifier: Operating System :: POSIX
Classifier: Programming Language :: Python :: 3
Classifier: Topic :: Internet :: WWW/HTTP
Classifier: Topic :: Software Development
Provides: pluggdapps
